{
  "required": true,
  "minVersion": "0.8",
  "package": "net.gudenau.minecraft.moretags.mixins",
  "compatibilityLevel": "JAVA_16",
  "mixins": [
    "bookshelves.EnchantingTableBlockMixin",
    "bookshelves.EnchantmentScreenHandlerMixin",
    "farmland.CropBlockMixin",
    "farmland.PlantBlockMixin",
    "farmland.RabbitEntity$EatCarrotCropGoal$DevMixin",
    "farmland.RabbitEntity$EatCarrotCropGoalMixin",
    "farmland.VillagerProfessionAccessor",
    "retro.OldTagApiSupport",
    "stickyblocks.PistonHandlerMixin"
  ],
  "client": [
    "maps.HeldItemRendererMixin",
    "maps.ItemFrameEntityRendererMixin"
  ],
  "plugin": "net.gudenau.minecraft.moretags.mixins.Plugin",
  "injectors": {
    "defaultRequire": 1
  }
}
